poc_my_tool_one/main.py
poc_my_tool_one-23.7.26.dist-info/METADATA
poc_my_tool_one-23.7.26.dist-info/WHEEL
poc_my_tool_one-23.7.26.dist-info/entry_points.txt
poc_my_tool_one-23.7.26.dist-info/RECORD
